<sdm:sdm xmlns:sdm="http://crownking/sdm" xmlns:xsi="http://www.w3.org/2001/XMLSchema-instance" xsi:schemaLocation="http://crownking/sdm ../../schema/sdm/sdm.xsd">
  <sdm:version sdm:filename="sdmICD4.xml" sdm:major="0" sdm:minor="0" sdm:rev="0"/>
  <sdm:devicecapabilities>
    <sdm:device sdm:devicename="PIC16F505" sdm:profile="16f"/>
    <sdm:device sdm:devicename="PIC16F506" sdm:profile="16f"/>
    <sdm:device sdm:devicename="PIC16F526" sdm:profile="16f"/>
    <sdm:device sdm:devicename="PIC16F527" sdm:profile="16f"/>
    <sdm:device sdm:devicename="PIC16F54" sdm:profile="empty"/>
    <sdm:device sdm:devicename="PIC16F57" sdm:profile="empty"/>
    <sdm:device sdm:devicename="PIC16F570" sdm:profile="16f"/>
    <sdm:device sdm:devicename="PIC16F59" sdm:profile="empty"/>
    <sdm:device sdm:devicename="PIC16F610" sdm:profile="16f"/>
    <sdm:device sdm:devicename="PIC16F616" sdm:profile="16f"/>
    <sdm:device sdm:devicename="PIC16F627" sdm:profile="empty"/>
    <sdm:device sdm:devicename="PIC16F627A" sdm:profile="16f"/>
    <sdm:device sdm:devicename="PIC16F628" sdm:profile="empty"/>
    <sdm:device sdm:devicename="PIC16F628A" sdm:profile="16f"/>
    <sdm:device sdm:devicename="PIC16F630" sdm:profile="16f"/>
    <sdm:device sdm:devicename="PIC16F631" sdm:profile="16f"/>
    <sdm:device sdm:devicename="PIC16F636" sdm:profile="16f"/>
    <sdm:device sdm:devicename="PIC16F639" sdm:profile="16f"/>
    <sdm:device sdm:devicename="PIC16F648A" sdm:profile="16f"/>
    <sdm:device sdm:devicename="PIC16F676" sdm:profile="16f"/>
    <sdm:device sdm:devicename="PIC16F677" sdm:profile="16f"/>
    <sdm:device sdm:devicename="PIC16F684" sdm:profile="16f"/>
    <sdm:device sdm:devicename="PIC16F685" sdm:profile="16f"/>
    <sdm:device sdm:devicename="PIC16F687" sdm:profile="16f"/>
    <sdm:device sdm:devicename="PIC16F688" sdm:profile="16f"/>
    <sdm:device sdm:devicename="PIC16F689" sdm:profile="16f"/>
    <sdm:device sdm:devicename="PIC16F690" sdm:profile="16f"/>
    <sdm:device sdm:devicename="PIC16F707" sdm:profile="16f"/>
    <sdm:device sdm:devicename="PIC16F716" sdm:profile="16f"/>
    <sdm:device sdm:devicename="PIC16F72" sdm:profile="empty"/>
    <sdm:device sdm:devicename="PIC16F720" sdm:profile="16f"/>
    <sdm:device sdm:devicename="PIC16F721" sdm:profile="16f"/>
    <sdm:device sdm:devicename="PIC16F722" sdm:profile="16f"/>
    <sdm:device sdm:devicename="PIC16F722A" sdm:profile="16f"/>
    <sdm:device sdm:devicename="PIC16F723" sdm:profile="16f"/>
    <sdm:device sdm:devicename="PIC16F723A" sdm:profile="16f"/>
    <sdm:device sdm:devicename="PIC16F724" sdm:profile="16f"/>
    <sdm:device sdm:devicename="PIC16F726" sdm:profile="16f"/>
    <sdm:device sdm:devicename="PIC16F727" sdm:profile="16f"/>
    <sdm:device sdm:devicename="PIC16F73" sdm:profile="empty"/>
    <sdm:device sdm:devicename="PIC16F737" sdm:profile="16f"/>
    <sdm:device sdm:devicename="PIC16F74" sdm:profile="empty"/>
    <sdm:device sdm:devicename="PIC16F747" sdm:profile="16f"/>
    <sdm:device sdm:devicename="PIC16F753" sdm:profile="16f"/>
    <sdm:device sdm:devicename="PIC16F76" sdm:profile="empty"/>
    <sdm:device sdm:devicename="PIC16F767" sdm:profile="16f"/>
    <sdm:device sdm:devicename="PIC16F77" sdm:profile="empty"/>
    <sdm:device sdm:devicename="PIC16F777" sdm:profile="16f"/>
    <sdm:device sdm:devicename="PIC16F785" sdm:profile="16f"/>
    <sdm:device sdm:devicename="PIC16F818" sdm:profile="16f"/>
    <sdm:device sdm:devicename="PIC16F819" sdm:profile="16f"/>
    <sdm:device sdm:devicename="PIC16F83" sdm:profile="empty"/>
    <sdm:device sdm:devicename="PIC16F84" sdm:profile="empty"/>
    <sdm:device sdm:devicename="PIC16F84A" sdm:profile="empty"/>
    <sdm:device sdm:devicename="PIC16F87" sdm:profile="16f"/>
    <sdm:device sdm:devicename="PIC16F870" sdm:profile="16f"/>
    <sdm:device sdm:devicename="PIC16F871" sdm:profile="16f"/>
    <sdm:device sdm:devicename="PIC16F872" sdm:profile="16f"/>
    <sdm:device sdm:devicename="PIC16F873" sdm:profile="16f"/>
    <sdm:device sdm:devicename="PIC16F873A" sdm:profile="16f"/>
    <sdm:device sdm:devicename="PIC16F874" sdm:profile="16f"/>
    <sdm:device sdm:devicename="PIC16F874A" sdm:profile="16f"/>
    <sdm:device sdm:devicename="PIC16F876" sdm:profile="16f"/>
    <sdm:device sdm:devicename="PIC16F876A" sdm:profile="16f"/>
    <sdm:device sdm:devicename="PIC16F877" sdm:profile="16f"/>
    <sdm:device sdm:devicename="PIC16F877A" sdm:profile="16f"/>
    <sdm:device sdm:devicename="PIC16F88" sdm:profile="16f"/>
    <sdm:device sdm:devicename="PIC16F882" sdm:profile="16f"/>
    <sdm:device sdm:devicename="PIC16F883" sdm:profile="16f"/>
    <sdm:device sdm:devicename="PIC16F884" sdm:profile="16f"/>
    <sdm:device sdm:devicename="PIC16F886" sdm:profile="16f"/>
    <sdm:device sdm:devicename="PIC16F887" sdm:profile="16f"/>
    <sdm:device sdm:devicename="PIC16F913" sdm:profile="16f"/>
    <sdm:device sdm:devicename="PIC16F914" sdm:profile="16f"/>
    <sdm:device sdm:devicename="PIC16F916" sdm:profile="16f"/>
    <sdm:device sdm:devicename="PIC16F917" sdm:profile="16f"/>
    <sdm:device sdm:devicename="PIC16F946" sdm:profile="16f"/>
    <sdm:device sdm:devicename="PIC16HV610" sdm:profile="16f"/>
    <sdm:device sdm:devicename="PIC16HV616" sdm:profile="16f"/>
    <sdm:device sdm:devicename="PIC16HV753" sdm:profile="16f"/>
    <sdm:device sdm:devicename="PIC16HV785" sdm:profile="16f"/>
    <sdm:device sdm:devicename="PIC16LF627" sdm:profile="empty"/>
    <sdm:device sdm:devicename="PIC16LF627A" sdm:profile="16f"/>
    <sdm:device sdm:devicename="PIC16LF628" sdm:profile="empty"/>
    <sdm:device sdm:devicename="PIC16LF628A" sdm:profile="16f"/>
    <sdm:device sdm:devicename="PIC16LF648A" sdm:profile="16f"/>
    <sdm:device sdm:devicename="PIC16LF707" sdm:profile="16f"/>
    <sdm:device sdm:devicename="PIC16LF720" sdm:profile="16f"/>
    <sdm:device sdm:devicename="PIC16LF721" sdm:profile="16f"/>
    <sdm:device sdm:devicename="PIC16LF722" sdm:profile="16f"/>
    <sdm:device sdm:devicename="PIC16LF722A" sdm:profile="16f"/>
    <sdm:device sdm:devicename="PIC16LF723" sdm:profile="16f"/>
    <sdm:device sdm:devicename="PIC16LF723A" sdm:profile="16f"/>
    <sdm:device sdm:devicename="PIC16LF724" sdm:profile="16f"/>
    <sdm:device sdm:devicename="PIC16LF726" sdm:profile="16f"/>
    <sdm:device sdm:devicename="PIC16LF727" sdm:profile="16f"/>
    <sdm:device sdm:devicename="PIC16LF74" sdm:profile="empty"/>
    <sdm:device sdm:devicename="PIC16LF747" sdm:profile="16f"/>
    <sdm:device sdm:devicename="PIC16LF76" sdm:profile="empty"/>
    <sdm:device sdm:devicename="PIC16LF767" sdm:profile="16f"/>
    <sdm:device sdm:devicename="PIC16LF77" sdm:profile="empty"/>
    <sdm:device sdm:devicename="PIC16LF777" sdm:profile="16f"/>
    <sdm:device sdm:devicename="PIC16LF818" sdm:profile="16f"/>
    <sdm:device sdm:devicename="PIC16LF819" sdm:profile="16f"/>
    <sdm:device sdm:devicename="PIC16LF83" sdm:profile="empty"/>
    <sdm:device sdm:devicename="PIC16LF84" sdm:profile="empty"/>
    <sdm:device sdm:devicename="PIC16LF84A" sdm:profile="empty"/>
    <sdm:device sdm:devicename="PIC16LF87" sdm:profile="16f"/>
    <sdm:device sdm:devicename="PIC16LF870" sdm:profile="16f"/>
    <sdm:device sdm:devicename="PIC16LF871" sdm:profile="16f"/>
    <sdm:device sdm:devicename="PIC16LF872" sdm:profile="16f"/>
    <sdm:device sdm:devicename="PIC16LF873" sdm:profile="16f"/>
    <sdm:device sdm:devicename="PIC16LF873A" sdm:profile="16f"/>
    <sdm:device sdm:devicename="PIC16LF874" sdm:profile="16f"/>
    <sdm:device sdm:devicename="PIC16LF874A" sdm:profile="16f"/>
    <sdm:device sdm:devicename="PIC16LF876" sdm:profile="16f"/>
    <sdm:device sdm:devicename="PIC16LF876A" sdm:profile="16f"/>
    <sdm:device sdm:devicename="PIC16LF877" sdm:profile="16f"/>
    <sdm:device sdm:devicename="PIC16LF877A" sdm:profile="16f"/>
    <sdm:device sdm:devicename="PIC16LF88" sdm:profile="16f"/>
  </sdm:devicecapabilities>
  <sdm:profiledef sdm:profilename="16f" sdm:profilesupported="no"/>
  <sdm:profiledef sdm:profilename="empty" sdm:profilesupported="no"/>
</sdm:sdm>
